{
  "logseq": [
    "baseInfo",
    "caller",
    "connected",
    "isMainUIVisible",
    "settings",
    "addListener",
    "beforeunload",
    "eventNames",
    "hideMainUI",
    "hideSettingsUI",
    "listenerCount",
    "listeners",
    "onSettingsChanged",
    "provideModel",
    "provideStyle",
    "provideTheme",
    "provideUI",
    "ready",
    "removeAllListeners",
    "removeListener",
    "resolveResourceFullUrl",
    "setMainUIAttrs",
    "setMainUIInlineStyle",
    "showMainUI",
    "showSettingsUI",
    "toggleMainUI",
    "updateSettings",
    "useSettingsSchema"
  ],
  "App": [
    "onBlockRendererSlotted",
    "onCurrentGraphChanged",
    "onMacroRendererSlotted",
    "onPageHeadActionsSlotted",
    "onRouteChanged",
    "onSidebarVisibleChanged",
    "onThemeModeChanged",
    "execGitCommand",
    "getCurrentGraph",
    "getInfo",
    "getStateFromStore",
    "getUserConfigs",
    "getUserInfo",
    "invokeExternalCommand",
    "openExternalLink",
    "pushState",
    "queryElementById",
    "queryElementRect",
    "quit",
    "registerCommand",
    "registerCommandPalette",
    "registerCommandShortcut",
    "registerPageMenuItem",
    "registerUIItem",
    "relaunch",
    "replaceState",
    "setFullScreen",
    "setLeftSidebarVisible",
    "setRightSidebarVisible",
    "setZoomFactor",
    "showMsg"
  ],
  "Editor": [
    "onInputSelectionEnd",
    "appendBlockInPage",
    "checkEditing",
    "createPage",
    "deletePage",
    "editBlock",
    "exitEditingMode",
    "getAllPages",
    "getBlock",
    "getBlockProperties",
    "getBlockProperty",
    "getCurrentBlock",
    "getCurrentPage",
    "getCurrentPageBlocksTree",
    "getEditingBlockContent",
    "getEditingCursorPosition",
    "getNextSiblingBlock",
    "getPage",
    "getPageBlocksTree",
    "getPageLinkedReferences",
    "getPagesFromNamespace",
    "getPagesTreeFromNamespace",
    "getPreviousSiblingBlock",
    "getSelectedBlocks",
    "insertAtEditingCursor",
    "insertBatchBlock",
    "insertBlock",
    "moveBlock",
    "openInRightSidebar",
    "prependBlockInPage",
    "registerBlockContextMenuItem",
    "registerSlashCommand",
    "removeBlock",
    "removeBlockProperty",
    "renamePage",
    "restoreEditingCursor",
    "scrollToBlockInPage",
    "setBlockCollapsed",
    "updateBlock",
    "upsertBlockProperty"
  ],
  "DB": [
    "onChanged",
    "datascriptQuery",
    "onBlockChanged",
    "q"
  ],
  "Git": [
    "execCommand",
    "loadIgnoreFile",
    "saveIgnoreFile"
  ],
  "UI": [
    "closeMsg",
    "showMsg"
  ],
  "Assets": [
    "listFilesOfCurrentGraph"
  ],
  "FileStorage": []
}